{"time": [2023, 10, 10, 13, 29, 21, 1, 283, 1], "topic": "solar/stats", "message": {"function": "READ", "model": "RNG-CTRL-ROVER", "battery_percentage": 100, "battery_voltage": 13.4, "battery_current": 13.700000000000001, "battery_temperature": 22, "controller_temperature": 36, "load_status": "off", "load_voltage": 0.0, "load_current": 0.0, "load_power": 0, "pv_voltage": 71.5, "pv_current": 2.67, "pv_power": 191, "max_charging_power_today": 371, "max_discharging_power_today": 0, "charging_amp_hours_today": 42, "discharging_amp_hours_today": 0, "power_generation_today": 563, "power_consumption_today": 0, "power_generation_total": 84485, "charging_status": "mppt", "battery_type": "lithium"}}
{"time": [2023, 10, 10, 13, 30, 21, 1, 283, 1], "topic": "solar/stats", "message": {"function": "READ", "model": "RNG-CTRL-ROVER", "battery_percentage": 100, "battery_voltage": 13.4, "battery_current": 11.870000000000001, "battery_temperature": 22, "controller_temperature": 36, "load_status": "off", "load_voltage": 0.0, "load_current": 0.0, "load_power": 0, "pv_voltage": 70.9, "pv_current": 2.34, "pv_power": 166, "max_charging_power_today": 371, "max_discharging_power_today": 0, "charging_amp_hours_today": 42, "discharging_amp_hours_today": 0, "power_generation_today": 563, "power_consumption_today": 0, "power_generation_total": 84485, "charging_status": "mppt", "battery_type": "lithium"}}
{"time": [2023, 10, 10, 13, 30, 59, 1, 283, 1], "topic": "solar/stats-batt", "message": {"function": "READ", "cell_count": 4, "cell_voltage_0": 3.3000000000000003, "cell_voltage_1": 3.3000000000000003, "cell_voltage_2": 3.3000000000000003, "cell_voltage_3": 3.3000000000000003, "sensor_count": 2, "temperature_0": 22.0, "temperature_1": 22.0, "current": -1.1, "voltage": 13.200000000000001, "remaining_charge": 106.60000000000001, "capacity": 200.0, "model": "RBT200LFP12-BT"}}
{"time": [2023, 10, 10, 13, 31, 21, 1, 283, 1], "topic": "solar/stats", "message": {"function": "READ", "model": "RNG-CTRL-ROVER", "battery_percentage": 100, "battery_voltage": 13.4, "battery_current": 11.94, "battery_temperature": 22, "controller_temperature": 36, "load_status": "off", "load_voltage": 0.0, "load_current": 0.0, "load_power": 0, "pv_voltage": 70.9, "pv_current": 2.35, "pv_power": 167, "max_charging_power_today": 371, "max_discharging_power_today": 0, "charging_amp_hours_today": 42, "discharging_amp_hours_today": 0, "power_generation_today": 563, "power_consumption_today": 0, "power_generation_total": 84485, "charging_status": "mppt", "battery_type": "lithium"}}
{"time": [2023, 10, 10, 13, 31, 59, 1, 283, 1], "topic": "solar/stats-batt", "message": {"function": "READ", "cell_count": 4, "cell_voltage_0": 3.3000000000000003, "cell_voltage_1": 3.3000000000000003, "cell_voltage_2": 3.3000000000000003, "cell_voltage_3": 3.3000000000000003, "sensor_count": 2, "temperature_0": 22.0, "temperature_1": 22.0, "current": -2.2, "voltage": 13.200000000000001, "remaining_charge": 106.60000000000001, "capacity": 200.0, "model": "RBT200LFP12-BT"}}
{"time": [2023, 10, 10, 13, 32, 21, 1, 283, 1], "topic": "solar/stats", "message": {"function": "READ", "model": "RNG-CTRL-ROVER", "battery_percentage": 100, "battery_voltage": 13.4, "battery_current": 11.790000000000001, "battery_temperature": 22, "controller_temperature": 36, "load_status": "off", "load_voltage": 0.0, "load_current": 0.0, "load_power": 0, "pv_voltage": 70.9, "pv_current": 2.32, "pv_power": 165, "max_charging_power_today": 371, "max_discharging_power_today": 0, "charging_amp_hours_today": 42, "discharging_amp_hours_today": 0, "power_generation_today": 563, "power_consumption_today": 0, "power_generation_total": 84485, "charging_status": "mppt", "battery_type": "lithium"}}
{"time": [2023, 10, 10, 13, 32, 59, 1, 283, 1], "topic": "solar/stats-batt", "message": {"function": "READ", "cell_count": 4, "cell_voltage_0": 3.3000000000000003, "cell_voltage_1": 3.3000000000000003, "cell_voltage_2": 3.3000000000000003, "cell_voltage_3": 3.3000000000000003, "sensor_count": 2, "temperature_0": 22.0, "temperature_1": 22.0, "current": -2.7, "voltage": 13.200000000000001, "remaining_charge": 106.60000000000001, "capacity": 200.0, "model": "RBT200LFP12-BT"}}
{"time": [2023, 10, 10, 13, 33, 21, 1, 283, 1], "topic": "solar/stats", "message": {"function": "READ", "model": "RNG-CTRL-ROVER", "battery_percentage": 100, "battery_voltage": 13.4, "battery_current": 10.39, "battery_temperature": 22, "controller_temperature": 36, "load_status": "off", "load_voltage": 0.0, "load_current": 0.0, "load_power": 0, "pv_voltage": 71.5, "pv_current": 2.02, "pv_power": 145, "max_charging_power_today": 371, "max_discharging_power_today": 0, "charging_amp_hours_today": 42, "discharging_amp_hours_today": 0, "power_generation_today": 563, "power_consumption_today": 0, "power_generation_total": 84485, "charging_status": "mppt", "battery_type": "lithium"}}
{"time": [2023, 10, 10, 13, 33, 59, 1, 283, 1], "topic": "solar/stats-batt", "message": {"function": "READ", "cell_count": 4, "cell_voltage_0": 3.3000000000000003, "cell_voltage_1": 3.3000000000000003, "cell_voltage_2": 3.3000000000000003, "cell_voltage_3": 3.3000000000000003, "sensor_count": 2, "temperature_0": 22.0, "temperature_1": 22.0, "current": -2.3000000000000003, "voltage": 13.200000000000001, "remaining_charge": 106.60000000000001, "capacity": 200.0, "model": "RBT200LFP12-BT"}}
{"time": [2023, 10, 10, 13, 34, 21, 1, 283, 1], "topic": "solar/stats", "message": {"function": "READ", "model": "RNG-CTRL-ROVER", "battery_percentage": 100, "battery_voltage": 13.4, "battery_current": 9.18, "battery_temperature": 22, "controller_temperature": 36, "load_status": "off", "load_voltage": 0.0, "load_current": 0.0, "load_power": 0, "pv_voltage": 70.4, "pv_current": 1.81, "pv_power": 128, "max_charging_power_today": 371, "max_discharging_power_today": 0, "charging_amp_hours_today": 43, "discharging_amp_hours_today": 0, "power_generation_today": 577, "power_consumption_today": 0, "power_generation_total": 84499, "charging_status": "mppt", "battery_type": "lithium"}}
{"time": [2023, 10, 10, 13, 34, 59, 1, 283, 1], "topic": "solar/stats-batt", "message": {"function": "READ", "cell_count": 4, "cell_voltage_0": 3.3000000000000003, "cell_voltage_1": 3.3000000000000003, "cell_voltage_2": 3.3000000000000003, "cell_voltage_3": 3.3000000000000003, "sensor_count": 2, "temperature_0": 22.0, "temperature_1": 22.0, "current": -3.3000000000000003, "voltage": 13.200000000000001, "remaining_charge": 106.60000000000001, "capacity": 200.0, "model": "RBT200LFP12-BT"}}
{"time": [2023, 10, 10, 13, 35, 21, 1, 283, 1], "topic": "solar/stats", "message": {"function": "READ", "model": "RNG-CTRL-ROVER", "battery_percentage": 100, "battery_voltage": 13.4, "battery_current": 8.27, "battery_temperature": 22, "controller_temperature": 36, "load_status": "off", "load_voltage": 0.0, "load_current": 0.0, "load_power": 0, "pv_voltage": 69.8, "pv_current": 1.6400000000000001, "pv_power": 115, "max_charging_power_today": 371, "max_discharging_power_today": 0, "charging_amp_hours_today": 43, "discharging_amp_hours_today": 0, "power_generation_today": 577, "power_consumption_today": 0, "power_generation_total": 84499, "charging_status": "mppt", "battery_type": "lithium"}}
{"time": [2023, 10, 10, 13, 35, 59, 1, 283, 1], "topic": "solar/stats-batt", "message": {"function": "READ", "cell_count": 4, "cell_voltage_0": 3.3000000000000003, "cell_voltage_1": 3.3000000000000003, "cell_voltage_2": 3.3000000000000003, "cell_voltage_3": 3.3000000000000003, "sensor_count": 2, "temperature_0": 22.0, "temperature_1": 22.0, "current": -4.1, "voltage": 13.200000000000001, "remaining_charge": 106.60000000000001, "capacity": 200.0, "model": "RBT200LFP12-BT"}}
{"time": [2023, 10, 10, 13, 36, 21, 1, 283, 1], "topic": "solar/stats", "message": {"function": "READ", "model": "RNG-CTRL-ROVER", "battery_percentage": 100, "battery_voltage": 13.4, "battery_current": 8.22, "battery_temperature": 23, "controller_temperature": 36, "load_status": "off", "load_voltage": 0.0, "load_current": 0.0, "load_power": 0, "pv_voltage": 71.0, "pv_current": 1.61, "pv_power": 115, "max_charging_power_today": 371, "max_discharging_power_today": 0, "charging_amp_hours_today": 43, "discharging_amp_hours_today": 0, "power_generation_today": 577, "power_consumption_today": 0, "power_generation_total": 84499, "charging_status": "mppt", "battery_type": "lithium"}}
{"time": [2023, 10, 10, 13, 36, 59, 1, 283, 1], "topic": "solar/stats-batt", "message": {"function": "READ", "cell_count": 4, "cell_voltage_0": 3.3000000000000003, "cell_voltage_1": 3.3000000000000003, "cell_voltage_2": 3.3000000000000003, "cell_voltage_3": 3.3000000000000003, "sensor_count": 2, "temperature_0": 22.0, "temperature_1": 22.0, "current": -3.5, "voltage": 13.200000000000001, "remaining_charge": 106.4, "capacity": 200.0, "model": "RBT200LFP12-BT"}}
{"time": [2023, 10, 10, 13, 37, 21, 1, 283, 1], "topic": "solar/stats", "message": {"function": "READ", "model": "RNG-CTRL-ROVER", "battery_percentage": 100, "battery_voltage": 13.4, "battery_current": 8.45, "battery_temperature": 23, "controller_temperature": 36, "load_status": "off", "load_voltage": 0.0, "load_current": 0.0, "load_power": 0, "pv_voltage": 70.4, "pv_current": 1.67, "pv_power": 118, "max_charging_power_today": 371, "max_discharging_power_today": 0, "charging_amp_hours_today": 43, "discharging_amp_hours_today": 0, "power_generation_today": 577, "power_consumption_today": 0, "power_generation_total": 84499, "charging_status": "mppt", "battery_type": "lithium"}}
{"time": [2023, 10, 10, 13, 37, 59, 1, 283, 1], "topic": "solar/stats-batt", "message": {"function": "READ", "cell_count": 4, "cell_voltage_0": 3.3000000000000003, "cell_voltage_1": 3.3000000000000003, "cell_voltage_2": 3.3000000000000003, "cell_voltage_3": 3.3000000000000003, "sensor_count": 2, "temperature_0": 22.0, "temperature_1": 22.0, "current": -4.2, "voltage": 13.200000000000001, "remaining_charge": 106.4, "capacity": 200.0, "model": "RBT200LFP12-BT"}}
{"time": [2023, 10, 10, 13, 38, 21, 1, 283, 1], "topic": "solar/stats", "message": {"function": "READ", "model": "RNG-CTRL-ROVER", "battery_percentage": 100, "battery_voltage": 13.4, "battery_current": 8.58, "battery_temperature": 22, "controller_temperature": 36, "load_status": "off", "load_voltage": 0.0, "load_current": 0.0, "load_power": 0, "pv_voltage": 70.4, "pv_current": 1.7, "pv_power": 120, "max_charging_power_today": 371, "max_discharging_power_today": 0, "charging_amp_hours_today": 43, "discharging_amp_hours_today": 0, "power_generation_today": 577, "power_consumption_today": 0, "power_generation_total": 84499, "charging_status": "mppt", "battery_type": "lithium"}}
{"time": [2023, 10, 10, 13, 38, 59, 1, 283, 1], "topic": "solar/stats-batt", "message": {"function": "READ", "cell_count": 4, "cell_voltage_0": 3.3000000000000003, "cell_voltage_1": 3.3000000000000003, "cell_voltage_2": 3.3000000000000003, "cell_voltage_3": 3.3000000000000003, "sensor_count": 2, "temperature_0": 22.0, "temperature_1": 22.0, "current": -4.6000000000000005, "voltage": 13.200000000000001, "remaining_charge": 106.4, "capacity": 200.0, "model": "RBT200LFP12-BT"}}
{"time": [2023, 10, 10, 13, 39, 21, 1, 283, 1], "topic": "solar/stats", "message": {"function": "READ", "model": "RNG-CTRL-ROVER", "battery_percentage": 100, "battery_voltage": 13.4, "battery_current": 8.620000000000001, "battery_temperature": 22, "controller_temperature": 36, "load_status": "off", "load_voltage": 0.0, "load_current": 0.0, "load_power": 0, "pv_voltage": 70.4, "pv_current": 1.7, "pv_power": 120, "max_charging_power_today": 371, "max_discharging_power_today": 0, "charging_amp_hours_today": 43, "discharging_amp_hours_today": 0, "power_generation_today": 577, "power_consumption_today": 0, "power_generation_total": 84499, "charging_status": "mppt", "battery_type": "lithium"}}
